bhaiapi/__init__.py
bhaiapi/chat.py
bhaiapi/constants.py
bhaiapi/core.py
bhaiapi/core_async.py
bhaiapi/core_cookies.py
bhaiapi/main.py
bhaiapi/utils.py
bhaiapi/chatbot/__init__.py
bhaiapi/chatbot/check.py
bhaiapi/chatbot/logo.py
bhaiapi/chatbot/news.py
bhaiapi/chatbot/open_app.py
bhaiapi/chatbot/weather.py
bhaiapi/chatbot/wiki.py
bhaiapi/models/__init__.py
bhaiapi/models/citation.py
bhaiapi/models/draft.py
bhaiapi/models/image.py
bhaiapi/models/result.py
bhaiapi/models/user_content.py
bhaiapi/models/tools/__init__.py
bhaiapi/models/tools/code.py
bhaiapi/models/tools/flight.py
bhaiapi/models/tools/gdocs.py
bhaiapi/models/tools/link.py
bhaiapi/models/tools/map.py
bhaiapi/models/tools/tool.py
bhaiapi/models/tools/tool_declaimer.py
bhaiapi/models/tools/youtube.py
bhaiapi-0.1.41.dist-info/LICENSE
bhaiapi-0.1.41.dist-info/METADATA
bhaiapi-0.1.41.dist-info/WHEEL
bhaiapi-0.1.41.dist-info/entry_points.txt
bhaiapi-0.1.41.dist-info/top_level.txt
bhaiapi-0.1.41.dist-info/RECORD
